Metadata-Version: 2.1
Name: MOGpy
Version: 0.0.5
Summary: Python lib for molecular genetic
Home-page: https://github.com/Lukas0025/MOGpy
Author: Lukáš Plevač
Author-email: lukas@plevac.eu
Classifier: Programming Language :: Python :: 3
Classifier: License :: OSI Approved :: Apache Software License
Classifier: Operating System :: OS Independent
Requires-Python: >=3.0
License-File: LICENSE.md
